README.md
setup.cfg
setup.py
polyutils/TRASH.py
polyutils/__init__.py
polyutils/generate_instances.py
polyutils/geometric_tools.py
polyutils/overlapping.py
polyutils/placement_rules.py
polyutils/polygon.py
polyutils/polyviewer3d.py
polyutils/rectangle.py
polyutils/triangle.py
polyutils/triangle_triangle_intersection.py
polyutils/voronoi_generator.py
polyutils.egg-info/PKG-INFO
polyutils.egg-info/SOURCES.txt
polyutils.egg-info/dependency_links.txt
polyutils.egg-info/requires.txt
polyutils.egg-info/top_level.txt